{
  "experiment": "token_position_analysis",
  "experiment_number": 109,
  "timestamp": "20260314_215009",
  "sequence_length": 280,
  "pooling_results": {
    "last": {
      "auroc": 1.0,
      "d": 71.24035768969568,
      "id_mean": 0.08684448003768921,
      "ood_mean": 0.37857631146907805,
      "id_std": 0.004095035928624339,
      "ood_std": 0.0721644029191761
    },
    "first": {
      "auroc": 0.5,
      "d": 0.0,
      "id_mean": 0.0,
      "ood_mean": 0.0,
      "id_std": 0.0,
      "ood_std": 0.0
    },
    "mean": {
      "auroc": 1.0,
      "d": 88.96785179315684,
      "id_mean": 0.013464272022247314,
      "ood_mean": 0.07108854949474334,
      "id_std": 0.0006476976504915807,
      "ood_std": 0.014528634542042892
    },
    "max": {
      "auroc": 1.0,
      "d": 22.998565970848905,
      "id_mean": 0.011322522163391113,
      "ood_mean": 0.0271905854344368,
      "id_std": 0.0006899587126998328,
      "ood_std": 0.0020211556598805545
    },
    "second_last": {
      "auroc": 1.0,
      "d": 26.52811971314302,
      "id_mean": 0.05911411046981811,
      "ood_mean": 0.2786998152732849,
      "id_std": 0.008277469512543848,
      "ood_std": 0.051238610347959505
    },
    "last_quarter_mean": {
      "auroc": 1.0,
      "d": 80.87635522776053,
      "id_mean": 0.036129599809646605,
      "ood_mean": 0.1422969549894333,
      "id_std": 0.0013127118153775255,
      "ood_std": 0.029480239874170342
    },
    "middle": {
      "auroc": 0.9575,
      "d": 2.835753434666449,
      "id_mean": 0.17715442776679993,
      "ood_mean": 0.3069139659404755,
      "id_std": 0.045758399268363385,
      "ood_std": 0.04468952124343395
    }
  },
  "position_results": {
    "0": {
      "auroc": 0.5,
      "d": 0.0
    },
    "14": {
      "auroc": 1.0,
      "d": 10.768232856022806
    },
    "28": {
      "auroc": 1.0,
      "d": 24.192976942447256
    },
    "42": {
      "auroc": 1.0,
      "d": 27.339176280992927
    },
    "56": {
      "auroc": 0.98,
      "d": 6.754004831588322
    },
    "70": {
      "auroc": 1.0,
      "d": 45.202527038889265
    },
    "84": {
      "auroc": 1.0,
      "d": 2.910626480047324
    },
    "98": {
      "auroc": 0.865,
      "d": 2.453233972552373
    },
    "112": {
      "auroc": 0.9575,
      "d": 4.176643113399481
    },
    "126": {
      "auroc": 1.0,
      "d": 31.77430998842991
    },
    "140": {
      "auroc": 0.9575,
      "d": 2.835753434666449
    },
    "154": {
      "auroc": 1.0,
      "d": 13.448649823655916
    },
    "168": {
      "auroc": 1.0,
      "d": 12.651520344913264
    },
    "182": {
      "auroc": 0.82,
      "d": 1.1930199024054398
    },
    "196": {
      "auroc": 0.99,
      "d": 8.645279606902262
    },
    "210": {
      "auroc": 0.9975,
      "d": 8.39333044191198
    },
    "224": {
      "auroc": 0.9975,
      "d": 3.8693774299331514
    },
    "238": {
      "auroc": 1.0,
      "d": 14.88989792765909
    },
    "252": {
      "auroc": 0.96,
      "d": 6.3061730196449215
    },
    "266": {
      "auroc": 1.0,
      "d": 54.35944765702006
    },
    "279": {
      "auroc": 1.0,
      "d": 71.24035768969568
    }
  }
}